LICENSE
MANIFEST.in
README.md
requirements.txt
setup.cfg
setup.py
kepingai/__init__.py
kepingai/api.py
kepingai/exceptions.py
kepingai/strategy.py
kepingai/user.py
kepingai_sdk.egg-info/PKG-INFO
kepingai_sdk.egg-info/SOURCES.txt
kepingai_sdk.egg-info/dependency_links.txt
kepingai_sdk.egg-info/requires.txt
kepingai_sdk.egg-info/top_level.txt