Metadata-Version: 2.1
Name: kepingai-sdk
Version: 0.0.3
Summary: # The Kepingai Platform API
Author: PT. Idabagus Engineering Indonesia
Author-email: support@kepingai.com
Maintainer: Ida Bagus Ratu Diaz Agasatya
Maintainer-email: diazagasatya@kepingai.com
License: UNKNOWN
Platform: UNKNOWN
Requires-Python: >=3.7
License-File: LICENSE
